macal/__about__.py
macal/__init__.py
macal/__main__.py
macal/ast.py
macal/ast_assignment.py
macal/ast_block.py
macal/ast_break.py
macal/ast_continue.py
macal/ast_expr.py
macal/ast_foreach.py
macal/ast_function_call.py
macal/ast_function_definition.py
macal/ast_halt.py
macal/ast_if.py
macal/ast_include.py
macal/ast_print.py
macal/ast_return.py
macal/ast_select.py
macal/ast_select_field.py
macal/ast_while.py
macal/exceptions.py
macal/interpreter.py
macal/lexer.py
macal/location.py
macal/macal.py
macal/mi.py
macal/mscope.py
macal/parser.py
macal/token.py
macal/types.py
macal/value_item.py
macal/variable.py
macal/Library/csv.mcl
macal/Library/debug.mcl
macal/Library/io.mcl
macal/Library/math.mcl
macal/Library/strings.mcl
macal/Library/syslog.mcl
macal/Library/system.mcl
macal/Library/time.mcl
macal/Library/Extern/ext_csv.py
macal/Library/Extern/ext_debug.py
macal/Library/Extern/ext_io.py
macal/Library/Extern/ext_math.py
macal/Library/Extern/ext_strings.py
macal/Library/Extern/ext_syslog.py
macal/Library/Extern/ext_system.py
macal/Library/Extern/ext_time.py
macal/examples/aor.mcl
macal/examples/array.mcl
macal/examples/array_and_record.mcl
macal/examples/break1.mcl
macal/examples/break2.mcl
macal/examples/const.mcl
macal/examples/continue1.mcl
macal/examples/continue2.mcl
macal/examples/csv.mcl
macal/examples/demo.mcl
macal/examples/demo_lib.mcl
macal/examples/ext.mcl
macal/examples/ext_lib.mcl
macal/examples/ext_lib.py
macal/examples/foreach1.mcl
macal/examples/foreach2.mcl
macal/examples/foreach3.mcl
macal/examples/functions.mcl
macal/examples/functions2.mcl
macal/examples/halt.mcl
macal/examples/helloworld.mcl
macal/examples/if.mcl
macal/examples/if2.mcl
macal/examples/if3.mcl
macal/examples/io.mcl
macal/examples/return.mcl
macal/examples/select1.mcl
macal/examples/select2.mcl
macal/examples/select3.mcl
macal/examples/select4.mcl
macal/examples/select5.mcl
macal/examples/select6.mcl
macal/examples/select7.mcl
macal/examples/select8.mcl
macal/examples/string.mcl
macal-4.0.82.dist-info/LICENSE.txt
macal-4.0.82.dist-info/METADATA
macal-4.0.82.dist-info/WHEEL
macal-4.0.82.dist-info/entry_points.txt
macal-4.0.82.dist-info/top_level.txt
macal-4.0.82.dist-info/RECORD
