Metadata-Version: 2.1
Name: macal
Version: 4.0.82
Summary: A proprietary scripting language
Author-email: Marco Caspers <marco.caspers@westcon.com>
Project-URL: Homepage, https://github.com/Sama-Developer/macal
Classifier: Programming Language :: Python :: 3
Classifier: License :: OSI Approved :: MIT License
Classifier: Operating System :: OS Independent
Requires-Python: >=3.7
License-File: LICENSE.txt
Requires-Dist: unidecode
